{
  "openapi": "3.0.1",
  "info": {
    "title": "API for Fiks-porten klienter",
    "description": "API for å administrere fiks-porten klienter",
    "contact": {
      "name": "Fiks-brukerstøtte",
      "url": "https://ks-no.github.io/",
      "email": "fiks-utvikling@ks.no"
    },
    "license": {
      "name": "MIT",
      "url": "https://opensource.org/licenses/MIT"
    },
    "version": "v1"
  },
  "servers": [
    {
      "url": "https://api.fiks.ks.no",
      "description": "KS Fiks API host",
      "variables": {}
    },
    {
      "url": "https://api.fiks.test.ks.no",
      "description": "KS Fiks TEST API host",
      "variables": {}
    }
  ],
  "paths": {},
  "components": {}
}